{"provinces":[{"code":"10000","name":"Antwerpen"},{"code":"20001","name":"Vlaams-Brabant"},{"code":"30000","name":"West-Vlaanderen"},{"code":"40000","name":"Oost-Vlaanderen"},{"code":"70000","name":"Limburg"}],"household_sizes":[{"code":"1","nl":"1 persoon"},{"code":"2","nl":"2 personen"},{"code":"3","nl":"3 personen"},{"code":"4+","nl":"4+ personen"}],"municipalities":[{"code":"41002","name":"Aalst (Aalst)"},{"code":"44084","name":"Aalter"},{"code":"24001","name":"Aarschot"},{"code":"11001","name":"Aartselaar"},{"code":"23105","name":"Affligem"},{"code":"73001","name":"Alken"},{"code":"38002","name":"Alveringem"},{"code":"11002","name":"Antwerpen"},{"code":"34002","name":"Anzegem"},{"code":"37020","name":"Ardooie"},{"code":"13001","name":"Arendonk"},{"code":"71002","name":"As"},{"code":"23002","name":"Asse"},{"code":"43002","name":"Assenede"},{"code":"34003","name":"Avelgem"},{"code":"13002","name":"Baarle-Hertog"},{"code":"13003","name":"Balen"},{"code":"31003","name":"Beernem"},{"code":"13004","name":"Beerse"},{"code":"23003","name":"Beersel"},{"code":"24007","name":"Begijnendijk"},{"code":"24008","name":"Bekkevoort"},{"code":"71004","name":"Beringen"},{"code":"12002","name":"Berlaar"},{"code":"42003","name":"Berlare"},{"code":"24009","name":"Bertem"},{"code":"23009","name":"Bever"},{"code":"46003","name":"Beveren (Sint-Niklaas)"},{"code":"24011","name":"Bierbeek"},{"code":"73006","name":"Bilzen"},{"code":"31004","name":"Blankenberge"},{"code":"72003","name":"Bocholt"},{"code":"11004","name":"Boechout"},{"code":"12005","name":"Bonheiden"},{"code":"11005","name":"Boom"},{"code":"24014","name":"Boortmeerbeek"},{"code":"73009","name":"Borgloon"},{"code":"12007","name":"Bornem"},{"code":"11007","name":"Borsbeek"},{"code":"24016","name":"Boutersem"},{"code":"45059","name":"Brakel"},{"code":"11008","name":"Brasschaat"},{"code":"11009","name":"Brecht"},{"code":"35002","name":"Bredene"},{"code":"72004","name":"Bree"},{"code":"31005","name":"Brugge"},{"code":"42004","name":"Buggenhout"},{"code":"31006","name":"Damme"},{"code":"35029","name":"De Haan"},{"code":"38008","name":"De Panne"},{"code":"44012","name":"De Pinte"},{"code":"34009","name":"Deerlijk"},{"code":"44083","name":"Deinze"},{"code":"41011","name":"Denderleeuw"},{"code":"42006","name":"Dendermonde"},{"code":"37002","name":"Dentergem"},{"code":"13006","name":"Dessel"},{"code":"44013","name":"Destelbergen"},{"code":"71011","name":"Diepenbeek"},{"code":"24020","name":"Diest"},{"code":"32003","name":"Diksmuide"},{"code":"23016","name":"Dilbeek"},{"code":"72041","name":"Dilsen-Stokkem"},{"code":"23098","name":"Drogenbos"},{"code":"12009","name":"Duffel"},{"code":"11013","name":"Edegem"},{"code":"43005","name":"Eeklo"},{"code":"41082","name":"Erpe-Mere"},{"code":"11016","name":"Essen"},{"code":"44019","name":"Evergem"},{"code":"23023","name":"Galmaarden"},{"code":"44020","name":"Gavere"},{"code":"13008","name":"Geel"},{"code":"24028","name":"Geetbets"},{"code":"71016","name":"Genk"},{"code":"44021","name":"Gent"},{"code":"41018","name":"Geraardsbergen"},{"code":"71017","name":"Gingelom"},{"code":"35005","name":"Gistel"},{"code":"24137","name":"Glabbeek"},{"code":"23024","name":"Gooik"},{"code":"23025","name":"Grimbergen"},{"code":"13010","name":"Grobbendonk"},{"code":"24033","name":"Haacht"},{"code":"41024","name":"Haaltert"},{"code":"71020","name":"Halen"},{"code":"23027","name":"Halle (Halle-Vilvoorde)"},{"code":"71069","name":"Ham"},{"code":"42008","name":"Hamme (Dendermonde)"},{"code":"72037","name":"Hamont-Achel"},{"code":"34013","name":"Harelbeke"},{"code":"71022","name":"Hasselt"},{"code":"72038","name":"Hechtel-Eksel"},{"code":"73022","name":"Heers"},{"code":"12014","name":"Heist-op-den-Berg"},{"code":"11018","name":"Hemiksem"},{"code":"24038","name":"Herent"},{"code":"13011","name":"Herentals"},{"code":"13012","name":"Herenthout"},{"code":"71024","name":"Herk-de-Stad"},{"code":"23032","name":"Herne"},{"code":"13013","name":"Herselt"},{"code":"73028","name":"Herstappe"},{"code":"41027","name":"Herzele"},{"code":"71070","name":"Heusden-Zolder"},{"code":"33039","name":"Heuvelland"},{"code":"24041","name":"Hoegaarden"},{"code":"23033","name":"Hoeilaart"},{"code":"73032","name":"Hoeselt"},{"code":"24043","name":"Holsbeek"},{"code":"36006","name":"Hooglede"},{"code":"13014","name":"Hoogstraten"},{"code":"45062","name":"Horebeke"},{"code":"72039","name":"Houthalen-Helchteren"},{"code":"32006","name":"Houthulst"},{"code":"11021","name":"Hove (Antwerpen)"},{"code":"24045","name":"Huldenberg"},{"code":"13016","name":"Hulshout"},{"code":"35006","name":"Ichtegem"},{"code":"33011","name":"Ieper"},{"code":"36007","name":"Ingelmunster"},{"code":"36008","name":"Izegem"},{"code":"31012","name":"Jabbeke"},{"code":"11022","name":"Kalmthout"},{"code":"23038","name":"Kampenhout"},{"code":"23039","name":"Kapelle-op-den-Bos"},{"code":"11023","name":"Kapellen (Antwerpen)"},{"code":"43007","name":"Kaprijke"},{"code":"13017","name":"Kasterlee"},{"code":"24048","name":"Keerbergen"},{"code":"72018","name":"Kinrooi"},{"code":"45060","name":"Kluisbergen"},{"code":"31043","name":"Knokke-Heist"},{"code":"32010","name":"Koekelare"},{"code":"38014","name":"Koksijde"},{"code":"11024","name":"Kontich"},{"code":"32011","name":"Kortemark"},{"code":"24054","name":"Kortenaken"},{"code":"24055","name":"Kortenberg"},{"code":"73040","name":"Kortessem"},{"code":"34022","name":"Kortrijk"},{"code":"23099","name":"Kraainem"},{"code":"46013","name":"Kruibeke"},{"code":"45068","name":"Kruisem"},{"code":"34023","name":"Kuurne"},{"code":"13053","name":"Laakdal"},{"code":"42010","name":"Laarne"},{"code":"73042","name":"Lanaken"},{"code":"24059","name":"Landen"},{"code":"33040","name":"Langemark-Poelkapelle"},{"code":"42011","name":"Lebbeke"},{"code":"41034","name":"Lede"},{"code":"36010","name":"Ledegem"},{"code":"34025","name":"Lendelede"},{"code":"23104","name":"Lennik"},{"code":"71034","name":"Leopoldsburg"},{"code":"24062","name":"Leuven"},{"code":"36011","name":"Lichtervelde"},{"code":"23044","name":"Liedekerke"},{"code":"12021","name":"Lier"},{"code":"45063","name":"Lierde"},{"code":"44085","name":"Lievegem"},{"code":"13019","name":"Lille"},{"code":"23100","name":"Linkebeek"},{"code":"11025","name":"Lint"},{"code":"24133","name":"Linter"},{"code":"32030","name":"Lo-Reninge"},{"code":"44034","name":"Lochristi"},{"code":"46014","name":"Lokeren"},{"code":"72020","name":"Lommel"},{"code":"23045","name":"Londerzeel"},{"code":"24066","name":"Lubbeek"},{"code":"71037","name":"Lummen"},{"code":"45064","name":"Maarkedal"},{"code":"72021","name":"Maaseik"},{"code":"73107","name":"Maasmechelen"},{"code":"23047","name":"Machelen (Halle-Vilvoorde)"},{"code":"43010","name":"Maldegem"},{"code":"11057","name":"Malle"},{"code":"12025","name":"Mechelen"},{"code":"13021","name":"Meerhout"},{"code":"23050","name":"Meise"},{"code":"44040","name":"Melle"},{"code":"34027","name":"Menen"},{"code":"23052","name":"Merchtem"},{"code":"44043","name":"Merelbeke"},{"code":"13023","name":"Merksplas"},{"code":"33016","name":"Mesen"},{"code":"37007","name":"Meulebeke"},{"code":"35011","name":"Middelkerke"},{"code":"44045","name":"Moerbeke (Gent)"},{"code":"13025","name":"Mol"},{"code":"36012","name":"Moorslede"},{"code":"11029","name":"Mortsel"},{"code":"44048","name":"Nazareth"},{"code":"11030","name":"Niel"},{"code":"71045","name":"Nieuwerkerken (Hasselt)"},{"code":"38016","name":"Nieuwpoort"},{"code":"12026","name":"Nijlen"},{"code":"41048","name":"Ninove"},{"code":"13029","name":"Olen"},{"code":"35013","name":"Oostende"},{"code":"44052","name":"Oosterzele"},{"code":"31022","name":"Oostkamp"},{"code":"37010","name":"Oostrozebeke"},{"code":"23060","name":"Opwijk"},{"code":"24086","name":"Oud-Heverlee"},{"code":"13031","name":"Oud-Turnhout"},{"code":"45035","name":"Oudenaarde"},{"code":"35014","name":"Oudenburg"},{"code":"72042","name":"Oudsbergen"},{"code":"23062","name":"Overijse"},{"code":"72030","name":"Peer"},{"code":"72043","name":"Pelt"},{"code":"23064","name":"Pepingen"},{"code":"37011","name":"Pittem"},{"code":"33021","name":"Poperinge"},{"code":"12029","name":"Putte"},{"code":"12041","name":"Puurs-Sint-Amands"},{"code":"11035","name":"Ranst"},{"code":"13035","name":"Ravels"},{"code":"13036","name":"Retie"},{"code":"73066","name":"Riemst"},{"code":"13037","name":"Rijkevorsel"},{"code":"36015","name":"Roeselare"},{"code":"45041","name":"Ronse"},{"code":"23097","name":"Roosdaal"},{"code":"24094","name":"Rotselaar"},{"code":"37012","name":"Ruiselede"},{"code":"11037","name":"Rumst"},{"code":"11038","name":"Schelle"},{"code":"24134","name":"Scherpenheuvel-Zichem"},{"code":"11039","name":"Schilde"},{"code":"11040","name":"Schoten"},{"code":"23101","name":"Sint-Genesius-Rode"},{"code":"46020","name":"Sint-Gillis-Waas"},{"code":"12035","name":"Sint-Katelijne-Waver"},{"code":"43014","name":"Sint-Laureins"},{"code":"41063","name":"Sint-Lievens-Houtem"},{"code":"44064","name":"Sint-Martens-Latem"},{"code":"46021","name":"Sint-Niklaas (Sint-Niklaas)"},{"code":"23077","name":"Sint-Pieters-Leeuw"},{"code":"71053","name":"Sint-Truiden"},{"code":"34043","name":"Spiere-Helkijn"},{"code":"11044","name":"Stabroek"},{"code":"36019","name":"Staden"},{"code":"23081","name":"Steenokkerzeel"},{"code":"46024","name":"Stekene"},{"code":"46025","name":"Temse"},{"code":"23086","name":"Ternat"},{"code":"24104","name":"Tervuren"},{"code":"71057","name":"Tessenderlo"},{"code":"37015","name":"Tielt (Tielt)"},{"code":"24135","name":"Tielt-Winge"},{"code":"24107","name":"Tienen"},{"code":"73083","name":"Tongeren"},{"code":"31033","name":"Torhout"},{"code":"24109","name":"Tremelo"},{"code":"13040","name":"Turnhout"},{"code":"38025","name":"Veurne"},{"code":"23088","name":"Vilvoorde"},{"code":"33041","name":"Vleteren"},{"code":"73109","name":"Voeren"},{"code":"13044","name":"Vorselaar"},{"code":"13046","name":"Vosselaar"},{"code":"42023","name":"Waasmunster"},{"code":"44073","name":"Wachtebeke"},{"code":"34040","name":"Waregem"},{"code":"73098","name":"Wellen"},{"code":"23102","name":"Wemmel"},{"code":"33029","name":"Wervik"},{"code":"13049","name":"Westerlo"},{"code":"42025","name":"Wetteren"},{"code":"34041","name":"Wevelgem"},{"code":"23103","name":"Wezembeek-Oppem"},{"code":"42026","name":"Wichelen"},{"code":"37017","name":"Wielsbeke"},{"code":"11050","name":"Wijnegem"},{"code":"12040","name":"Willebroek"},{"code":"37018","name":"Wingene"},{"code":"11052","name":"Wommelgem"},{"code":"45061","name":"Wortegem-Petegem"},{"code":"11053","name":"Wuustwezel"},{"code":"11054","name":"Zandhoven"},{"code":"23094","name":"Zaventem"},{"code":"31040","name":"Zedelgem"},{"code":"42028","name":"Zele"},{"code":"43018","name":"Zelzate"},{"code":"23096","name":"Zemst"},{"code":"11055","name":"Zoersel"},{"code":"71066","name":"Zonhoven"},{"code":"33037","name":"Zonnebeke"},{"code":"41081","name":"Zottegem"},{"code":"24130","name":"Zoutleeuw"},{"code":"31042","name":"Zuienkerke"},{"code":"44081","name":"Zulte"},{"code":"71067","name":"Zutendaal"},{"code":"45065","name":"Zwalm"},{"code":"34042","name":"Zwevegem"},{"code":"11056","name":"Zwijndrecht"}]}